evil_pkg/__init__.py
evil_pkg-0.1.dist-info/METADATA
evil_pkg-0.1.dist-info/WHEEL
evil_pkg-0.1.dist-info/top_level.txt
evil_pkg-0.1.dist-info/RECORD
