Metadata-Version: 2.2
Name: evil-pkg
Version: 0.1
Summary: Just a harmless package :)
Dynamic: summary
